pixelplot/__init__.py
pixelplot/dashedimagedraw.py
pixelplot/metadata.py
pixelplot/plotter.py
pixelplot-1.0.1.dist-info/LICENSE
pixelplot-1.0.1.dist-info/METADATA
pixelplot-1.0.1.dist-info/WHEEL
pixelplot-1.0.1.dist-info/top_level.txt
pixelplot-1.0.1.dist-info/RECORD
